s3upload/__init__.py
s3upload/apps.py
s3upload/fields.py
s3upload/src/.babelrc
s3upload/src/app/actions/index.js
s3upload/src/app/components/index.js
s3upload/src/app/constants/index.js
s3upload/src/app/index.js
s3upload/src/app/reducers/appStatus.js
s3upload/src/app/reducers/awsUploadsParams.js
s3upload/src/app/reducers/index.js
s3upload/src/app/store/connect.js
s3upload/src/app/store/index.js
s3upload/src/app/utils/index.js
s3upload/src/package-lock.json
s3upload/src/package.json
s3upload/static/s3upload/css/bootstrap-progress.min.css
s3upload/static/s3upload/css/styles.css
s3upload/static/s3upload/js/django-s3-uploads.js
s3upload/static/s3upload/js/django-s3-uploads.min.js
s3upload/templates/s3upload/s3upload-widget.tpl
s3upload/urls.py
s3upload/utils.py
s3upload/views.py
s3upload/widgets.py
django_s3_upload-1.2.0.dist-info/METADATA
django_s3_upload-1.2.0.dist-info/WHEEL
django_s3_upload-1.2.0.dist-info/licenses/LICENSE
django_s3_upload-1.2.0.dist-info/RECORD
